README.md
setup.py
pyeon/__init__.py
pyeon/pyeon.py
pyeon.egg-info/PKG-INFO
pyeon.egg-info/SOURCES.txt
pyeon.egg-info/dependency_links.txt
pyeon.egg-info/not-zip-safe
pyeon.egg-info/top_level.txt