Metadata-Version: 2.1
Name: pyeon
Version: 0.0.3
Summary: Generates some phrases when someone goes to the convenience store.
Home-page: http://github.com/qria/pyeon
Author: MinJune Kim
Author-email: qria@qria.net
License: MIT
Platform: UNKNOWN
Classifier: Programming Language :: Python :: 3
Classifier: License :: OSI Approved :: MIT License
Classifier: Operating System :: OS Independent
